{"quoteResponse":{"result":[{"language":"en-US","region":"US","quoteType":"EQUITY","typeDisp":"Equity","quoteSourceName":"Delayed Quote","triggerable":false,"customPriceAlertConfidence":"NONE","messageBoardId":"finmb_875770","gmtOffSetMilliseconds":7200000,"currency":"EUR","exchangeTimezoneShortName":"CEST","exchange":"VIE","shortName":"LENZING AG","market":"at_market","longName":"Lenzing Aktiengesellschaft","exchangeTimezoneName":"Europe/Amsterdam","esgPopulated":false,"firstTradeDateMilliseconds":946886100000,"priceHint":2,"regularMarketChange":2.0999985,"regularMarketChangePercent":2.4561386,"regularMarketTime":1653665728,"regularMarketPrice":87.6,"regularMarketDayHigh":87.6,"regularMarketDayRange":"85.6 - 87.6","regularMarketDayLow":85.6,"regularMarketVolume":10571,"regularMarketPreviousClose":85.5,"bid":0.0,"ask":0.0,"bidSize":152,"askSize":310,"fullExchangeName":"Vienna","financialCurrency":"EUR","regularMarketOpen":86.4,"averageDailyVolume3Month":28905,"averageDailyVolume10Day":14075,"fiftyTwoWeekLowChange":10.299995,"fiftyTwoWeekLowChangePercent":0.13324702,"fiftyTwoWeekRange":"77.3 - 134.2","fiftyTwoWeekHighChange":-46.6,"fiftyTwoWeekHighChangePercent":-0.34724292,"fiftyTwoWeekLow":77.3,"fiftyTwoWeekHigh":134.2,"dividendDate":20217600,"marketState":"CLOSED","tradeable":false,"earningsTimestamp":1659490200,"earningsTimestampStart":1659490200,"earningsTimestampEnd":1659490200,"trailingAnnualDividendRate":4.35,"trailingPE":22.415558,"trailingAnnualDividendYield":0.05087719,"epsTrailingTwelveMonths":3.908,"epsForward":5.25,"sharesOutstanding":26550000,"bookValue":44.363,"fiftyDayAverage":88.608,"fiftyDayAverageChange":-1.0080032,"fiftyDayAverageChangePercent":-0.011375984,"twoHundredDayAverage":103.5835,"twoHundredDayAverageChange":-15.983505,"twoHundredDayAverageChangePercent":-0.1543055,"marketCap":2325779968,"forwardPE":16.685715,"priceToBook":1.9746186,"sourceInterval":15,"exchangeDataDelayedBy":15,"averageAnalystRating":"2.2 - Buy","symbol":"LNZ.VI"}],"error":null}}